rnumpy/__init__.py
rnumpy/_version.py
rnumpy-0.0.1.dist-info/LICENSE
rnumpy-0.0.1.dist-info/WHEEL
rnumpy-0.0.1.dist-info/METADATA
rnumpy-0.0.1.dist-info/RECORD
