Metadata-Version: 2.1
Name: rnumpy
Version: 0.0.1
Summary: RNumPy
Home-page: https://github.com/Quansight-Labs/rnumpy
License: UNKNOWN
Author: Ralf Gommers
Author-email: ralf.gommers@gmail.com
Requires-Python: >=3.6
Classifier: Intended Audience :: Developers
Classifier: License :: OSI Approved :: BSD License
Classifier: Programming Language :: Python :: 3
Classifier: Topic :: Software Development :: Libraries :: Python Modules
Requires-Dist: numpy >= 1.16.4
Requires-Dist: sphinx; extra == "doc"
Requires-Dist: pytest; extra == "test"
Provides-Extra: doc
Provides-Extra: test
